macollector/__init__.py
macollector/config_manager.py
macollector/data_processor.py
macollector/device_manager.py
macollector/exceptions.py
macollector/exporters.py
macollector/file_processors.py
macollector/logging_setup.py
macollector/macollector.py
macollector/network_device.py
macollector/utilities.py
macollector-1.3.1.dist-info/LICENSE
macollector-1.3.1.dist-info/METADATA
macollector-1.3.1.dist-info/WHEEL
macollector-1.3.1.dist-info/RECORD
