Metadata-Version: 2.1
Name: macollector
Version: 1.3.1
Summary: Python-based tool developed to streamline the collection of MAC addresses from Cisco network switches.
Home-page: https://github.com/TheZay/Radius_Integration.git
License: GPL-3.0-or-later
Keywords: networking,cisco,mac,mac-address,switches,network,automation
Author: Noah Keller
Author-email: nkeller@choctawnation.com
Requires-Python: >=3.8,<4.0
Classifier: License :: OSI Approved :: GNU General Public License v3 or later (GPLv3+)
Classifier: Programming Language :: Python :: 3
Classifier: Programming Language :: Python :: 3.8
Classifier: Programming Language :: Python :: 3.9
Classifier: Programming Language :: Python :: 3.10
Classifier: Programming Language :: Python :: 3.11
Classifier: Programming Language :: Python :: 3.12
Requires-Dist: bcrypt (>=4.1.2,<5.0.0)
Requires-Dist: cffi (>=1.16.0,<2.0.0)
Requires-Dist: cryptography (>=41.0.7,<42.0.0)
Requires-Dist: future (>=0.18.3,<0.19.0)
Requires-Dist: ipaddress (>=1.0.23,<2.0.0)
Requires-Dist: netmiko (>=4.3.0,<5.0.0)
Requires-Dist: ntc-templates (>=4.1.0,<5.0.0)
Requires-Dist: paramiko (>=3.4.0,<4.0.0)
Requires-Dist: pycparser (>=2.21,<3.0)
Requires-Dist: pynacl (>=1.5.0,<2.0.0)
Requires-Dist: pyyaml (>=6.0.1,<7.0.0)
Requires-Dist: scp (>=0.14.5,<0.15.0)
Requires-Dist: six (>=1.16.0,<2.0.0)
Requires-Dist: textfsm (>=1.1.3,<2.0.0)
Project-URL: Bug Tracker, https://github.com/TheZay/Radius_Integration/issues
Project-URL: Documentation, https://github.com/TheZay/Radius_Integration/tree/main/docs
Project-URL: Repository, https://github.com/TheZay/Radius_Integration.git
